bokicast_mcp_server/__init__.py
bokicast_mcp_server/main.py
bokicast_mcp_server/mod_account_entry_widget.py
bokicast_mcp_server/mod_bokicast_service.py
bokicast_mcp_server/mod_bs_pl_widget.py
bokicast_mcp_server/mod_journal_entry_widget.py
bokicast_mcp_server/mod_service.py
bokicast_mcp_server/mod_t_account_widget.py
bokicast_mcp_server-0.0.1.dist-info/licenses/LICENSE
bokicast_mcp_server-0.0.1.dist-info/METADATA
bokicast_mcp_server-0.0.1.dist-info/WHEEL
bokicast_mcp_server-0.0.1.dist-info/entry_points.txt
bokicast_mcp_server-0.0.1.dist-info/top_level.txt
bokicast_mcp_server-0.0.1.dist-info/RECORD
