Metadata-Version: 2.4
Name: bokicast-mcp-server
Version: 0.0.1
Summary: Bokicast MCP Server is an MCP server designed for a brand-new style of bookkeeping study.
Author-email: Aska Lanclaude <crypto.tuber.magika@gmail.com>
License-Expression: Apache-2.0
Project-URL: Homepage, https://github.com/lambda-tuber/bokicast-mcp-server
Keywords: accounting,boki,MCP,FastMCP,TTS,AI,voice synthesis
Requires-Python: >=3.11
License-File: LICENSE
Requires-Dist: mcp>=0.1.0
Requires-Dist: requests>=2.31.0
Requires-Dist: numpy>=1.24.0
Requires-Dist: PySide6>=6.9.3
Requires-Dist: pygetwindow>=0.0.9
Requires-Dist: pyyaml>=6.0.3
Requires-Dist: Pillow>=11.3.0
Provides-Extra: dev
Requires-Dist: pytest>=8.0.0; extra == "dev"
Requires-Dist: pytest-asyncio>=0.23.0; extra == "dev"
Dynamic: license-file
